[
  {
    "id": "DP_QCS_38_SUBMISSIONS",
    "event_id": "qingchuang",
    "label": "第38届青创赛申报规模",
    "year": "2023",
    "value": "第38届大赛共收到14205份申报材料，其中青少年科技创新成果板块11346项。",
    "source_ids": [
      "SRC_QCS_SHITALENT_38"
    ],
    "public_use": "可公开使用，适合写成“参赛作品超1.4万件”。",
    "agent_use": "用于说明青创赛不是小范围展示，而是全市级大规模筛选。"
  },
  {
    "id": "DP_QCS_38_FINALIST",
    "event_id": "qingchuang",
    "label": "第38届青创赛终审问辩入围",
    "year": "2023",
    "value": "青少年科技创新成果板块11346项申报中，700项入围终审问辩，约6.17%。",
    "source_ids": [
      "SRC_QCS_SHITALENT_38",
      "SRC_QCS_SHSID_38_AWARD"
    ],
    "public_use": "可公开使用，但引用入围率时建议标注来源；SHSID为学校公开喜报，不能替代赛事组委会。",
    "agent_use": "用于说明“终评入围更低”，比只说获奖率更能体现筛选强度。"
  },
  {
    "id": "DP_QCS_40_SCALE",
    "event_id": "qingchuang",
    "label": "第40届青创赛现行规模",
    "year": "2025",
    "value": "第40届大赛收到来自全市700余所中小学5000余名参赛选手提交的4200余件作品，近400件科创作品及100余幅科幻画作品入围现场活动。",
    "source_ids": [
      "SRC_QCS_CAST_40"
    ],
    "public_use": "可公开使用，适合近年口径。",
    "agent_use": "用于说明规则近年更加注重学生本人能力和现场活动。"
  },
  {
    "id": "DP_QCS_41_SCALE",
    "event_id": "qingchuang",
    "label": "第41届青创赛最新规模",
    "year": "2026",
    "value": "第41届上海市青少年科技创新大赛现场活动于2026年3月27日至29日在上海科学会堂举行，吸引近700所学校、5400余名青少年参与，累计提交科技创新项目和科学幻想绘画作品4500余件；400件科技创新作品和192件科幻画作品入围现场活动，280余位专家参与评审，44家单位设立专项奖。",
    "source_ids": [
      "SRC_QCS_41_CAST"
    ],
    "public_use": "可公开使用，适合做2026最新规模口径；不要和第40届数据混写。",
    "agent_use": "用于说明青创赛最新规模、现场问辩和多维评价机制。"
  },
  {
    "id": "DP_QCS_41_TIMELINE",
    "event_id": "qingchuang",
    "label": "第41届青创赛申报和结果节点",
    "year": "2026",
    "value": "第41届申报期为2026年1月1日8:00至1月20日24:00；1月下旬至3月上旬进行资格、原创、伦理审查和专家初评；3月下旬现场活动；4月公示并公布结果。官方通知明确：本赛事不纳入上海市中学生综合素质评价。",
    "source_ids": [
      "SRC_QCS_41_NOTICE"
    ],
    "public_use": "可公开用于时间线复盘和下一届备赛参考；具体当年报名仍需以官方新通知为准。",
    "agent_use": "用于提醒顾问不要把赛事结果说成综评承诺。"
  },
  {
    "id": "DP_CHUYING_2023_SCALE",
    "event_id": "chuying",
    "label": "2023雏鹰杯申报和获奖规模",
    "year": "2023",
    "value": "2023年活动收到16个区800余所中小学申报的4300余个项目，评出各奖项课题1300余件，最终10位队员获特等奖并被授予上海少年科学院小院士称号。",
    "source_ids": [
      "SRC_CHUYING_CYOL_2024"
    ],
    "public_use": "可公开使用，适合视频数据页。",
    "agent_use": "用于说明“项目数量大、评审层级多、最终小院士非常稀缺”。"
  },
  {
    "id": "DP_CHUYING_HISTORY",
    "event_id": "chuying",
    "label": "上海少年科学院小院士历史沉淀",
    "year": "2003-2023",
    "value": "自2003年首届上海少年科学院小院士命名以来，已产生244名上海小院士、616名全国小院士、12名全国十佳小院士以及9名市长奖获得者。",
    "source_ids": [
      "SRC_CHUYING_CYOL_2024"
    ],
    "public_use": "可公开使用，但建议作为背景小字，不要堆在主口播里。",
    "agent_use": "用于说明赛事背后有长期培养体系。"
  },
  {
    "id": "DP_CHUYING_2025_FINAL",
    "event_id": "chuying",
    "label": "2025年度雏鹰杯/第23届小院士终评",
    "year": "2025/2026",
    "value": "2025年“雏鹰杯”红领巾科创小能手暨第二十三届上海少年科学院“小院士”交流展示活动终评及颁奖于2026年1月举行；按项目类别取前3%的项目入围终评，最终10位少先队员获上海少年科学院“小院士”称号。",
    "source_ids": [
      "SRC_CHUYING_EASTDAY_2025",
      "SRC_CHUYING_BAOSHAN_2025"
    ],
    "public_use": "可公开使用，但目前为媒体/政务号公开报道；如做强官方背书，后续优先补团市委或少工委原文。",
    "agent_use": "用于最新雏鹰杯筛选强度和小院士稀缺度。"
  },
  {
    "id": "DP_CHUYING_2025_THEMES",
    "event_id": "chuying",
    "label": "2025年度雏鹰杯主题和项目方向",
    "year": "2025/2026",
    "value": "2025年度活动以“红领巾爱科学”为主题，项目设置涵盖创造发明、自然生态、智慧城市、航空航天、人工智能、创新创意、其他类别，并增设“智慧关怀”“智学未来”“智行上海”三大专项。",
    "source_ids": [
      "SRC_CHUYING_EASTDAY_2025"
    ],
    "public_use": "可公开用于内容选题和家长解释，但不宜写成官方固定年度规则。",
    "agent_use": "用于把雏鹰杯讲成真实问题、城市议题和少年表达结合的赛事。"
  },
  {
    "id": "DP_SCLACI_NATIONAL_STATUS",
    "event_id": "sclaci",
    "label": "宋庆龄发明奖官方定位",
    "year": "2023修订章程",
    "value": "宋庆龄少年儿童发明奖设立于2001年，是经科技部批准的公益性国家级青少年科技活动奖项，被列入教育部面向中小学生的全国性竞赛活动名单。",
    "source_ids": [
      "SRC_SCLACI_CHARTER"
    ],
    "public_use": "可公开使用，适合赛事介绍页。",
    "agent_use": "用于说明赛事含金量，不建议改写成升学承诺。"
  },
  {
    "id": "DP_SCLACI_20_SCALE",
    "event_id": "sclaci",
    "label": "第二十届宋庆龄发明奖参评和获奖规模",
    "year": "2025",
    "value": "第二十届共有5.7万余名青少年、4.6万余件作品参评，获奖作品590件，其中发明作品346件、人工智能编程作品183件、创意作品61件。",
    "source_ids": [
      "SRC_SCLACI_20_AWARD_NEWS",
      "SRC_PEOPLE_20"
    ],
    "public_use": "可公开使用，适合视频数据页。",
    "agent_use": "用于说明全国性奖项竞争密度更高；可粗略说“590/4.6万+”，但不要暗示官方公布了获奖率。"
  },
  {
    "id": "DP_SCLACI_21_SCHEDULE",
    "event_id": "sclaci",
    "label": "第二十一届宋庆龄发明奖2026赛程",
    "year": "2026",
    "value": "第二十一届宋庆龄少年儿童发明奖于2026年举办：2月至3月各地组织机构选拔推荐，3月至4月作品申报及形式审核，5月至6月全国初评，6月/7月入围终评作品名单公示，7月发布终评通知，8月终评颁奖。",
    "source_ids": [
      "SRC_SCLACI_21_NOTICE"
    ],
    "public_use": "可公开用于备赛时间线，实际报名仍以各组织机构通知为准。",
    "agent_use": "用于顾问提醒备赛节点和申报节奏。"
  },
  {
    "id": "DP_SCLACI_21_CATEGORIES",
    "event_id": "sclaci",
    "label": "第二十一届宋庆龄发明奖类别和申报限制",
    "year": "2026",
    "value": "第二十一届作品类别包括发明作品、人工智能（编程）作品、创意作品（太空旅行、未来能源）和科技绘画作品征集；小学组发明、AI、创意作品须为四年级及以上，作品创作完成时间须为2025年9月1日之后，每位学生限一项作品类别一件作品，不接受食品、医药类项目以及科学研究论文类作品。",
    "source_ids": [
      "SRC_SCLACI_21_NOTICE"
    ],
    "public_use": "可公开用于规则解读；不要替代各地区组织机构的具体报送要求。",
    "agent_use": "用于判断产品交付是否匹配类别、年龄和作品限制。"
  },
  {
    "id": "DP_LAB_92_INTERNAL",
    "event_id": "lab_package",
    "label": "Lab赛事包团队综合上岸率",
    "year": "内部口径",
    "value": "Lab赛事包团队综合上岸率：92%+。",
    "source_ids": [
      "SRC_INTERNAL_SUPPLEMENT"
    ],
    "public_use": "可用于内部颁奖视频，但对外发布前需确认分母、统计期和隐私边界。",
    "agent_use": "作为产品结果口径使用；禁止展开最低值剔除、具体老师、复杂均值算法。"
  },
  {
    "id": "DP_SAIFU_16_POSITIONING",
    "event_id": "saifu_chuangzhi",
    "label": "第16届赛复创智杯官方定位",
    "year": "2025",
    "value": "第十六届“赛复创智杯”以“我创意、我快乐”为主题，展示活动注重科技创意设计过程的合理性，对是否已完成或实施不作具体要求，未完成作品只需注明实施或试验所受的时间、场地、设施与技术等条件限制。",
    "source_ids": [
      "SRC_SAIFU_16_NOTICE"
    ],
    "public_use": "可公开使用，适合赛事介绍页和“创意方案也能参赛”的核心卖点。",
    "agent_use": "用于把赛复讲成低门槛创意设计赛事，与青创赛、宋庆龄发明奖等实作/研究型赛事区分。"
  },
  {
    "id": "DP_SAIFU_16_TIMELINE",
    "event_id": "saifu_chuangzhi",
    "label": "第16届赛复创智杯赛程",
    "year": "2025",
    "value": "第十六届活动启动5~6月；项目申报7月1日8:00至9月8日12:00；赛区选拔9月21日16点前；赛区报送9月25日11点前；初评9月27日；复评10月中旬（暂定10月12日）；终评11月中旬（暂定11月15日）。",
    "source_ids": [
      "SRC_SAIFU_16_NOTICE"
    ],
    "public_use": "可公开用于备赛时间线，下一届需以当年通知为准。",
    "agent_use": "用于顾问提醒暑假备赛窗口：6月构思、7-8月打磨、9月初提交。"
  },
  {
    "id": "DP_SAIFU_16_CATEGORIES",
    "event_id": "saifu_chuangzhi",
    "label": "第16届赛复创智杯作品类别和申报限制",
    "year": "2025",
    "value": "作品分为A类方案设计演示类、B类模型创意演示类、C类虚拟动画演示类。A类提交创意设计文稿；B类提交文稿和3张模型照片；C类提交文稿和MP4或PPT演示文件。每位学生每个类别限报1项，集体作品不超过3人且同一学段，辅导教师不超过2人。",
    "source_ids": [
      "SRC_SAIFU_16_NOTICE"
    ],
    "public_use": "可公开用于规则解读和学生能力匹配。",
    "agent_use": "用于把孩子表达、动手、动画/演示能力分别匹配到A/B/C三类作品。"
  },
  {
    "id": "DP_SAIFU_15_SCALE",
    "event_id": "saifu_chuangzhi",
    "label": "第15届赛复创智杯规模和终评",
    "year": "2024",
    "value": "第十五届“赛复创智杯”自5月启动以来得到2万余名学生响应，经过各赛区初评，最终向市组委会推荐1283项；10月13日复评中来自全市16个区及长三角地区的279个项目在三大类7个小组中展示交流，84项创意作品入围终评；终评产生5项特等奖和2项特等项目提名奖。",
    "source_ids": [
      "SRC_SAIFU_SSEDF_15"
    ],
    "public_use": "可公开用于说明赛事规模、覆盖范围和终评筛选强度。",
    "agent_use": "用于视频数据页和家长说明，不要把历史数据直接推导为下一届获奖概率。"
  },
  {
    "id": "DP_SAIFU_16_EVALUATION",
    "event_id": "saifu_chuangzhi",
    "label": "第16届赛复创智杯评审原则和查新边界",
    "year": "2025",
    "value": "评审原则包括跨越性、新颖性、可观性。不可申报两类作品：已经参加过前几届且无显著改进的作品；已经存在现有产品又无显著创意改进设计的作品。",
    "source_ids": [
      "SRC_SAIFU_16_NOTICE",
      "SRC_SAIFU_SOHU_14"
    ],
    "public_use": "可公开用于参赛避坑和查新指导。",
    "agent_use": "用于提醒顾问/家长先做电商、专利和论文查新，避免与现成产品撞车。"
  }
]
